fund/__init__.py
utils/__init__.py
utils/date_u.py
utils/formula.py
oxshare-0.0.1.dist-info/METADATA
oxshare-0.0.1.dist-info/WHEEL
oxshare-0.0.1.dist-info/top_level.txt
oxshare-0.0.1.dist-info/RECORD
