Metadata-Version: 2.1
Name: oxshare
Version: 0.0.1
Summary: a utility for crawling financial data.
Home-page: https://github.com/Shen-Yu/oxshare
Author: Eric Shen
Author-email: shenyu@hotmail.com
License: UNKNOWN
Project-URL: Bug Tracker, https://github.com/Shen-Yu/oxshare/issues
Platform: UNKNOWN
Classifier: Programming Language :: Python :: 3
Classifier: License :: OSI Approved :: MIT License
Classifier: Operating System :: OS Independent
Requires-Python: >=3.6
